enola/__init__.py
enola/enola_types.py
enola/evaluation.py
enola/get_executions.py
enola/step.py
enola/tracking.py
enola/tracking_batch.py
enola/base/__init__.py
enola/base/connect.py
enola/base/common/__init__.py
enola/base/common/huemul_common.py
enola/base/common/huemul_connection.py
enola/base/common/huemul_datetime_part.py
enola/base/common/huemul_error.py
enola/base/common/huemul_functions.py
enola/base/common/huemul_http_info.py
enola/base/common/huemul_logging.py
enola/base/common/huemul_param.py
enola/base/common/huemul_response_error.py
enola/base/common/huemul_response_provider.py
enola/base/common/huemul_response_to_bloc.py
enola/base/common/auth/__init__.py
enola/base/common/auth/auth_model.py
enola/base/common/auth/auth_service_bloc.py
enola/base/common/auth/auth_service_model.py
enola/base/common/auth/auth_service_provider.py
enola/base/internal/__init__.py
enola/base/internal/evaluation/enola_evaluation.py
enola/base/internal/evaluation/enola_evaluation_bloc.py
enola/base/internal/evaluation/enola_evaluation_provider.py
enola/base/internal/executions/enola_execution.py
enola/base/internal/executions/enola_execution_bloc.py
enola/base/internal/executions/enola_execution_provider.py
enola/base/internal/tracking/enola_tracking.py
enola/base/internal/tracking/enola_tracking_bloc.py
enola/base/internal/tracking/enola_tracking_provider.py
enola/base/internal/tracking_batch/enola_tracking_batch.py
enola/base/internal/tracking_batch/enola_tracking_batch_bloc.py
enola/base/internal/tracking_batch/enola_tracking_batch_provider.py
enola-1.3.5.dist-info/METADATA
enola-1.3.5.dist-info/WHEEL
enola-1.3.5.dist-info/licenses/LICENSE
enola-1.3.5.dist-info/RECORD
