Metadata-Version: 2.3
Name: enola
Version: 1.3.5
Summary: Enola-AI is a GenAI platform for validating and monitoring AI models in regulated industries like finance, healthcare, and education. It ensures compliance with strict standards via continuous user feedback, automated assessments, and expert reviews.
Project-URL: Homepage, https://github.com/huemulsolutions/enola
Project-URL: Bug Tracker, https://github.com/huemulsolutions/enola/issues
Author-email: Sebastian Rodriguez Robotham <sebastian.rodriguez@huemulsolutions.com>, Developer Code <developer.code@huemulsolutions.com>
License-File: LICENSE
Keywords: AI,Intelligence,Observability,agent
Classifier: License :: OSI Approved :: MIT License
Classifier: Operating System :: OS Independent
Classifier: Programming Language :: Python :: 3
Requires-Python: >=3.7
Requires-Dist: jsonpickle>=3.0.0
Requires-Dist: pandas==2.2.0
Requires-Dist: pyjwt>=2.8.0
Requires-Dist: requests>=2.25.1
